{"v":0,"docs":{"tokens-colors--docs":{"id":"tokens-colors--docs","name":"Docs","path":"./stories/Colors.mdx","title":"Tokens/Colors","content":"import { Meta } from '@storybook/addon-docs/blocks';\n\n<Meta title=\"Tokens/Colors\" />\n\n# Colors\n\nThe Atlas color palette.\n\nexport const Swatch = ({ name, hex }) => (\n  <div style={{\n    display: 'flex',\n    alignItems: 'center',\n    gap: '16px',\n    padding: '12px 0',\n    borderBottom: '1px solid rgba(15,15,15,0.06)',\n  }}>\n    <div style={{\n      width: '48px',\n      height: '48px',\n      borderRadius: '8px',\n      backgroundColor: hex,\n      border: '1px solid rgba(15,15,15,0.08)',\n      flexShrink: 0,\n    }} />\n    <div>\n      <div style={{ fontWeight: 600, fontSize: '15px' }}>{name}</div>\n      <code style={{ fontSize: '13px', color: 'rgba(15,15,15,0.5)' }}>{hex}</code>\n    </div>\n  </div>\n);\n\n## Accent\n\n<Swatch name=\"Yellow\" hex=\"#F6FF00\" />\n<Swatch name=\"Purple\" hex=\"#9500FF\" />\n<Swatch name=\"Blue\" hex=\"#00AAFF\" />\n\n## Surface\n\n<Swatch name=\"Surface Light\" hex=\"#F4F4F4\" />\n<Swatch name=\"Surface Dark\" hex=\"#333333\" />\n\n## Text\n\n<Swatch name=\"Text Primary\" hex=\"#0F0F0F\" />\n<Swatch name=\"Text Light\" hex=\"#FAFAFA\" />\n\n---\n\n### Usage\n\n```js\nimport { colors } from '@atlas/tokens';\n\n// colors.yellow   → '#F6FF00'\n// colors.purple   → '#9500FF'\n// colors.blue     → '#00AAFF'\n```\n\n```css\n:root {\n  --yellow: #F6FF00;\n  --purple: #9500FF;\n  --blue: #00AAFF;\n  --bg-surface: #F4F4F4;\n  --bg-surface-dark: #333333;\n  --text-primary: #0F0F0F;\n  --text-light: #FAFAFA;\n}\n```\n"},"assets-flags--docs":{"id":"assets-flags--docs","name":"Docs","path":"./stories/Flags.mdx","title":"Assets/Flags","content":"import { Meta } from '@storybook/addon-docs/blocks';\n\n<Meta title=\"Assets/Flags\" />\n\n# Flags\n\n271 SVG country flags in two aspect ratios, named by ISO 3166-1 alpha-2 code.\n\nexport const Flag = ({ code, name }) => (\n  <div style={{\n    display: 'inline-flex',\n    flexDirection: 'column',\n    alignItems: 'center',\n    gap: '6px',\n    padding: '12px',\n    borderRadius: '8px',\n    width: '90px',\n    textAlign: 'center',\n  }}>\n    <img\n      src={`https://tickertapenews.github.io/atlas/flags/4x3/${code}.svg`}\n      alt={name}\n      style={{ width: '48px', height: '36px', borderRadius: '3px', border: '1px solid rgba(15,15,15,0.08)' }}\n    />\n    <div style={{ fontSize: '12px', fontWeight: 600 }}>{code.toUpperCase()}</div>\n    <div style={{ fontSize: '11px', color: 'rgba(15,15,15,0.45)' }}>{name}</div>\n  </div>\n);\n\n## Nordic\n\n<div style={{ display: 'flex', flexWrap: 'wrap', gap: '4px' }}>\n  <Flag code=\"se\" name=\"Sverige\" />\n  <Flag code=\"no\" name=\"Norge\" />\n  <Flag code=\"dk\" name=\"Danmark\" />\n  <Flag code=\"fi\" name=\"Finland\" />\n  <Flag code=\"is\" name=\"Island\" />\n</div>\n\n## Europe\n\n<div style={{ display: 'flex', flexWrap: 'wrap', gap: '4px' }}>\n  <Flag code=\"gb\" name=\"UK\" />\n  <Flag code=\"de\" name=\"Tyskland\" />\n  <Flag code=\"fr\" name=\"Frankrike\" />\n  <Flag code=\"nl\" name=\"Nederländerna\" />\n  <Flag code=\"ch\" name=\"Schweiz\" />\n  <Flag code=\"it\" name=\"Italien\" />\n  <Flag code=\"es\" name=\"Spanien\" />\n  <Flag code=\"pt\" name=\"Portugal\" />\n  <Flag code=\"at\" name=\"Österrike\" />\n  <Flag code=\"be\" name=\"Belgien\" />\n  <Flag code=\"ie\" name=\"Irland\" />\n  <Flag code=\"pl\" name=\"Polen\" />\n  <Flag code=\"eu\" name=\"EU\" />\n</div>\n\n## Americas\n\n<div style={{ display: 'flex', flexWrap: 'wrap', gap: '4px' }}>\n  <Flag code=\"us\" name=\"USA\" />\n  <Flag code=\"ca\" name=\"Kanada\" />\n  <Flag code=\"br\" name=\"Brasilien\" />\n  <Flag code=\"mx\" name=\"Mexiko\" />\n  <Flag code=\"ar\" name=\"Argentina\" />\n</div>\n\n## Asia & Pacific\n\n<div style={{ display: 'flex', flexWrap: 'wrap', gap: '4px' }}>\n  <Flag code=\"jp\" name=\"Japan\" />\n  <Flag code=\"cn\" name=\"Kina\" />\n  <Flag code=\"kr\" name=\"Sydkorea\" />\n  <Flag code=\"in\" name=\"Indien\" />\n  <Flag code=\"au\" name=\"Australien\" />\n  <Flag code=\"sg\" name=\"Singapore\" />\n  <Flag code=\"hk\" name=\"Hongkong\" />\n  <Flag code=\"tw\" name=\"Taiwan\" />\n</div>\n\n---\n\n### Formats\n\n| Aspect | Path | Use case |\n|--------|------|----------|\n| 4:3 | `/flags/4x3/{code}.svg` | Standard flag |\n| 1:1 | `/flags/1x1/{code}.svg` | Icons, avatars |\n\n### Usage\n\n```html\n<img src=\"https://tickertapenews.github.io/atlas/flags/4x3/se.svg\" alt=\"SE\" width=\"24\">\n```\n"},"assets-icons--docs":{"id":"assets-icons--docs","name":"Docs","path":"./stories/Icons.mdx","title":"Assets/Icons","content":"import { Meta } from '@storybook/addon-docs/blocks';\n\n<Meta title=\"Assets/Icons\" />\n\n# Icons\n\n1,383 regular + 288 solid SVG icons from [Iconoir](https://iconoir.com) (v7.11, MIT license).\n\nexport const Icon = ({ name, style = 'regular' }) => (\n  <div style={{\n    display: 'inline-flex',\n    flexDirection: 'column',\n    alignItems: 'center',\n    gap: '6px',\n    padding: '12px 8px',\n    width: '100px',\n    textAlign: 'center',\n    borderRadius: '6px',\n    cursor: 'default',\n  }}>\n    <img\n      src={`https://tickertapenews.github.io/atlas/icons/${style}/${name}.svg`}\n      alt={name}\n      style={{ width: '24px', height: '24px' }}\n    />\n    <span style={{ fontSize: '10px', color: 'rgba(15,15,15,0.45)', wordBreak: 'break-all', lineHeight: 1.3 }}>{name}</span>\n  </div>\n);\n\n## Navigation\n\n<div style={{ display: 'flex', flexWrap: 'wrap', gap: '2px' }}>\n  <Icon name=\"arrow-left\" />\n  <Icon name=\"arrow-right\" />\n  <Icon name=\"arrow-up\" />\n  <Icon name=\"arrow-down\" />\n  <Icon name=\"arrow-up-right\" />\n  <Icon name=\"home\" />\n  <Icon name=\"home-simple\" />\n  <Icon name=\"search\" />\n  <Icon name=\"filter\" />\n  <Icon name=\"filter-list\" />\n  <Icon name=\"share-ios\" />\n  <Icon name=\"bookmark\" />\n</div>\n\n## Actions\n\n<div style={{ display: 'flex', flexWrap: 'wrap', gap: '2px' }}>\n  <Icon name=\"plus\" />\n  <Icon name=\"minus\" />\n  <Icon name=\"check\" />\n  <Icon name=\"check-circle\" />\n  <Icon name=\"edit\" />\n  <Icon name=\"edit-pencil\" />\n  <Icon name=\"trash\" />\n  <Icon name=\"download\" />\n  <Icon name=\"upload\" />\n  <Icon name=\"eye\" />\n  <Icon name=\"eye-closed\" />\n  <Icon name=\"lock\" />\n</div>\n\n## Communication\n\n<div style={{ display: 'flex', flexWrap: 'wrap', gap: '2px' }}>\n  <Icon name=\"mail\" />\n  <Icon name=\"mail-open\" />\n  <Icon name=\"bell\" />\n  <Icon name=\"bell-notification\" />\n  <Icon name=\"bell-off\" />\n</div>\n\n## User\n\n<div style={{ display: 'flex', flexWrap: 'wrap', gap: '2px' }}>\n  <Icon name=\"user\" />\n  <Icon name=\"user-circle\" />\n  <Icon name=\"user-plus\" />\n  <Icon name=\"user-star\" />\n  <Icon name=\"user-badge-check\" />\n</div>\n\n## Finance\n\n<div style={{ display: 'flex', flexWrap: 'wrap', gap: '2px' }}>\n  <Icon name=\"dollar\" />\n  <Icon name=\"dollar-circle\" />\n  <Icon name=\"euro\" />\n  <Icon name=\"graph-up\" />\n  <Icon name=\"graph-down\" />\n  <Icon name=\"chart-line\" />\n  <Icon name=\"stats-up-square\" />\n  <Icon name=\"stats-down-square\" />\n</div>\n\n## Time\n\n<div style={{ display: 'flex', flexWrap: 'wrap', gap: '2px' }}>\n  <Icon name=\"clock\" />\n  <Icon name=\"calendar\" />\n  <Icon name=\"calendar-check\" />\n  <Icon name=\"calendar-plus\" />\n</div>\n\n## Media\n\n<div style={{ display: 'flex', flexWrap: 'wrap', gap: '2px' }}>\n  <Icon name=\"star\" />\n  <Icon name=\"heart\" />\n  <Icon name=\"settings\" />\n  <Icon name=\"airplay\" />\n</div>\n\n---\n\n### Formats\n\n| Style | Count | Path |\n|-------|-------|------|\n| Regular (outline) | 1,383 | `/icons/regular/{name}.svg` |\n| Solid (filled) | 288 | `/icons/solid/{name}.svg` |\n\n### Usage\n\n```html\n<!-- Regular -->\n<img src=\"https://tickertapenews.github.io/atlas/icons/regular/search.svg\" width=\"24\" height=\"24\">\n\n<!-- Solid -->\n<img src=\"https://tickertapenews.github.io/atlas/icons/solid/heart.svg\" width=\"24\" height=\"24\">\n```\n\n### Browse all icons\n\nSee the full catalogue at [iconoir.com](https://iconoir.com). All icons are hosted at `/icons/regular/{name}.svg` using the same filenames.\n"},"introduction--docs":{"id":"introduction--docs","name":"Docs","path":"./stories/Introduction.mdx","title":"Introduction","content":"import { Meta } from '@storybook/addon-docs/blocks';\n\n<Meta title=\"Introduction\" />\n\n# Atlas Design System\n\nThe shared design system for **Ticker Tape News** and **The Desk**.\n\nAtlas centralizes components, design tokens, and assets so both projects stay visually consistent.\n\n---\n\n### What's inside\n\n| Section | Description |\n|---------|-------------|\n| **Colors** | Brand palette and surface colors |\n| **Typography** | Figtree font family and scale |\n| **Flags** | 271 SVG country flags in 4:3 and 1:1 |\n\n---\n\n### Quick start\n\nInstall Figtree and reference Atlas tokens:\n\n```html\n<link rel=\"preconnect\" href=\"https://fonts.googleapis.com\">\n<link rel=\"preconnect\" href=\"https://fonts.gstatic.com\" crossorigin>\n<link href=\"https://fonts.googleapis.com/css2?family=Figtree:ital,wght@0,300..900;1,300..900&display=swap\" rel=\"stylesheet\">\n```\n\nFlag usage:\n\n```html\n<img src=\"https://tickertapenews.github.io/atlas/flags/4x3/se.svg\" alt=\"SE\" width=\"24\">\n```\n"},"tokens-typography--docs":{"id":"tokens-typography--docs","name":"Docs","path":"./stories/Typography.mdx","title":"Tokens/Typography","content":"import { Meta } from '@storybook/addon-docs/blocks';\n\n<Meta title=\"Tokens/Typography\" />\n\n# Typography\n\nAtlas uses **Figtree** — a variable Google Font supporting weights 300–900 with italic.\n\nexport const Sample = ({ weight, size, label }) => (\n  <div style={{\n    fontFamily: '\"Figtree\", sans-serif',\n    fontWeight: weight,\n    fontSize: size || '24px',\n    padding: '12px 0',\n    borderBottom: '1px solid rgba(15,15,15,0.06)',\n    display: 'flex',\n    alignItems: 'baseline',\n    gap: '16px',\n  }}>\n    <span style={{ minWidth: '60px', fontSize: '13px', color: 'rgba(15,15,15,0.4)', fontWeight: 400 }}>{label}</span>\n    <span>The quick brown fox jumps over the lazy dog</span>\n  </div>\n);\n\n## Weights\n\n<Sample weight={300} label=\"300\" />\n<Sample weight={400} label=\"400\" />\n<Sample weight={500} label=\"500\" />\n<Sample weight={600} label=\"600\" />\n<Sample weight={700} label=\"700\" />\n<Sample weight={800} label=\"800\" />\n<Sample weight={900} label=\"900\" />\n\n## Scale\n\nexport const ScaleSample = ({ size, label }) => (\n  <div style={{\n    fontFamily: '\"Figtree\", sans-serif',\n    fontSize: size,\n    fontWeight: 500,\n    padding: '8px 0',\n    borderBottom: '1px solid rgba(15,15,15,0.06)',\n    display: 'flex',\n    alignItems: 'baseline',\n    gap: '16px',\n  }}>\n    <code style={{ minWidth: '80px', fontSize: '13px', color: 'rgba(15,15,15,0.4)', fontWeight: 400 }}>{label}</code>\n    <span>Ticker Tape News</span>\n  </div>\n);\n\n<ScaleSample size=\"12px\" label=\"12px\" />\n<ScaleSample size=\"14px\" label=\"14px\" />\n<ScaleSample size=\"16px\" label=\"16px\" />\n<ScaleSample size=\"20px\" label=\"20px\" />\n<ScaleSample size=\"24px\" label=\"24px\" />\n<ScaleSample size=\"32px\" label=\"32px\" />\n<ScaleSample size=\"48px\" label=\"48px\" />\n\n---\n\n### Load font\n\n```html\n<link rel=\"preconnect\" href=\"https://fonts.googleapis.com\">\n<link rel=\"preconnect\" href=\"https://fonts.gstatic.com\" crossorigin>\n<link href=\"https://fonts.googleapis.com/css2?family=Figtree:ital,wght@0,300..900;1,300..900&display=swap\" rel=\"stylesheet\">\n```\n\n```css\nbody {\n  font-family: 'Figtree', sans-serif;\n}\n```\n"}}}